profcomff_parse_lib/__init__.py
profcomff_parse_lib/dict_substitutions.py
profcomff_parse_lib/database/__init__.py
profcomff_parse_lib/database/add_lessons.py
profcomff_parse_lib/database/completion.py
profcomff_parse_lib/database/delete_lessons.py
profcomff_parse_lib/database/groups_to_array.py
profcomff_parse_lib/database/id_instead_name.py
profcomff_parse_lib/timetable/__init__.py
profcomff_parse_lib/timetable/calc_date.py
profcomff_parse_lib/timetable/flatten.py
profcomff_parse_lib/timetable/manual_edit.py
profcomff_parse_lib/timetable/multiple_lessons.py
profcomff_parse_lib/timetable/parse_all.py
profcomff_parse_lib/timetable/core/__init__.py
profcomff_parse_lib/timetable/core/parse_group.py
profcomff_parse_lib/timetable/core/parse_name.py
profcomff_parse_lib/timetable/core/parse_place.py
profcomff_parse_lib/timetable/core/parse_subjects.py
profcomff_parse_lib/timetable/core/parse_teacher.py
profcomff_parse_lib/timetable/core/parse_timetable.py
profcomff_parse_lib/timetable/core/pretty_subjects.py
profcomff_parse_lib/timetable/core/replace_lessons.py
profcomff_parse_lib/timetable/core/tests/__init__.py
profcomff_parse_lib/timetable/core/tests/parse_timetable_selected.py
profcomff_parse_lib/timetable/core/tests/test_parse_group.py
profcomff_parse_lib/timetable/core/tests/test_parse_name.py
profcomff_parse_lib/timetable/core/tests/test_parse_subjects.py
profcomff_parse_lib/timetable/core/tests/test_pretty_subjects.py
profcomff_parse_lib/utilities/__init__.py
profcomff_parse_lib/utilities/logger.py
profcomff_parse_lib/utilities/ndim_iterator.py
profcomff_parse_lib/utilities/urls_api.py
profcomff_parse_lib-2025.9.1.dist-info/licenses/LICENSE
tests/__init__.py
tests/test_calc_date.py
tests/test_flatten.py
tests/test_manual_edit.py
tests/test_multiple_lessons.py
profcomff_parse_lib-2025.9.1.dist-info/METADATA
profcomff_parse_lib-2025.9.1.dist-info/WHEEL
profcomff_parse_lib-2025.9.1.dist-info/top_level.txt
profcomff_parse_lib-2025.9.1.dist-info/RECORD
