Metadata-Version: 2.4
Name: profcomff_parse_lib
Version: 2025.9.1
Home-page: https://github.com/preparation-timetable-data 
Author: Sergey Zamyatin, Andrei Lukianov, Stanislav Roslavtsev
Classifier: Programming Language :: Python :: 3.11
License-File: LICENSE
Requires-Dist: requests
Requires-Dist: pandas
Requires-Dist: setuptools
Requires-Dist: retrying
Requires-Dist: beautifulsoup4
Dynamic: author
Dynamic: classifier
Dynamic: description
Dynamic: description-content-type
Dynamic: home-page
Dynamic: license-file
Dynamic: requires-dist
